quickda/__init__.py
quickda/clean_data.py
quickda/config.py
quickda/explore_categoric.py
quickda/explore_data.py
quickda/explore_numeric.py
quickda/explore_numeric_categoric.py
quickda/explore_time_series.py
quickda-0.2.2.dist-info/LICENSE
quickda-0.2.2.dist-info/METADATA
quickda-0.2.2.dist-info/WHEEL
quickda-0.2.2.dist-info/top_level.txt
quickda-0.2.2.dist-info/RECORD
