Metadata-Version: 2.1
Name: quickda
Version: 0.2.2
Summary: Simple & Easy-to-use python modules to perform Quick Exploratory Data Analysis for any structured dataset!
Home-page: https://github.com/sid-the-coder/QuickDA
Author: Sidheswar Venkatachalapathi
Author-email: gauty95@gmail.com
License: UNKNOWN
Platform: UNKNOWN
Classifier: Programming Language :: Python :: 3
Classifier: License :: OSI Approved :: MIT License
Classifier: Operating System :: OS Independent
Requires-Python: >=3.6
Requires-Dist: pandas
Requires-Dist: numpy
Requires-Dist: seaborn
Requires-Dist: matplotlib
Requires-Dist: pandas-profiling
Requires-Dist: ppscore
Requires-Dist: plotly
